xacc.pth
xacc/_pyxacc.so
xacc/xacc.py
xacc/xacc-config.cmake
xacc/.libs/libcurl-3aef6d7f.so.4.5.0
xacc/.libs/libz-a147dcb0.so.1.2.3
xacc/plugin_generator/plugin_generator.py
xacc/plugin_generator/templates/gate_instruction/README.md
xacc/plugin_generator/templates/gate_instruction/CMakeLists.txt
xacc/plugin_generator/templates/gate_instruction/instruction/{inst_class_name}.hpp
xacc/plugin_generator/templates/gate_instruction/instruction/manifest.json
xacc/plugin_generator/templates/gate_instruction/instruction/{inst_class_name}Activator.cpp
xacc/plugin_generator/templates/gate_instruction/instruction/CMakeLists.txt
xacc/plugin_generator/templates/gate_instruction/tests/CMakeLists.txt
xacc/plugin_generator/templates/gate_instruction/tests/{inst_class_name}Tester.cpp
xacc/plugin_generator/templates/irtransformation/README.md
xacc/plugin_generator/templates/irtransformation/CMakeLists.txt
xacc/plugin_generator/templates/irtransformation/transformation/manifest.json
xacc/plugin_generator/templates/irtransformation/transformation/{irt_class_name}Activator.cpp
xacc/plugin_generator/templates/irtransformation/transformation/CMakeLists.txt
xacc/plugin_generator/templates/irtransformation/transformation/{irt_class_name}.cpp
xacc/plugin_generator/templates/irtransformation/transformation/{irt_class_name}.hpp
xacc/plugin_generator/templates/irtransformation/tests/CMakeLists.txt
xacc/plugin_generator/templates/irtransformation/tests/{irt_class_name}Tester.cpp
xacc/plugin_generator/templates/compiler/README.md
xacc/plugin_generator/templates/compiler/CMakeLists.txt
xacc/plugin_generator/templates/compiler/tests/{compiler_class_name}Tester.cpp
xacc/plugin_generator/templates/compiler/tests/CMakeLists.txt
xacc/plugin_generator/templates/compiler/compiler/manifest.json
xacc/plugin_generator/templates/compiler/compiler/{compiler_class_name}.hpp
xacc/plugin_generator/templates/compiler/compiler/CMakeLists.txt
xacc-0.1.16.dist-info/top_level.txt
xacc-0.1.16.dist-info/DESCRIPTION.rst
xacc-0.1.16.dist-info/METADATA
xacc-0.1.16.dist-info/WHEEL
xacc-0.1.16.dist-info/RECORD
xacc-0.1.16.dist-info/metadata.json
